[
  {
    "id": "admin_부당한_표시_또는_광고로_보지_아니하_0001",
    "text": "부당한 표시 또는 광고로 보지 아니하는 식품등의 기능성 표시 또는 광고에 관한 규정\n부당한 표시 또는 광고로 보지 아니하는 식품등의 기능성 표시 또는 광고에 관한 규정\n[시행 2025. 1. 1.] [식품의약품안전처고시 제2024-62호, 2024. 10. 17., 일부개정]  제1조(목적)  제2조(정의)  제3조(적용범위)  제4조(기능성의 범위)  제5조(식품등의 요건)  제5조의2(기준의 적용)  제6조(표시 또는 광고의 방법)  제7조(자료 공개 등)  제8조(재검토 기한)\n\n\n부당한 표시 또는 광고로 보지 아니하는 식품등의 기능성 표시 또는 광고에 관한 규정\n부당한 표시 또는 광고로 보지 아니하는 식품등의 기능성 표시\n또는 광고에 관한 규정\n[시행 2025. 1. 1.] [식품의약품안전처고시 제2024-62호, 2024. 10. 17., 일부개정]  식품의약품안전처(식품표시광고정책과), 043-719-2181  제1조(목적) 이 고시는 「식품 등의 표시ᆞ광고에 관한 법률」제8조 및 같은 법 시행령 제3조제1항 별표 1 제3호나목\n에 따라 제품에 함유된 영양성분이나 원재료가 신체조직과 기능의 증진에 도움을 줄 수 있다는 내용으로써 부당\n한 표시 또는",
    "metadata": {
      "law": "부당한 표시 또는 광고로 보지 아니하는 식품등의 기능성 표시 또는 광고에 관한 규정",
      "law_number": "2024-62호",
      "category": "admin_rule",
      "chunk_index": 1,
      "total_chunks": 28,
      "effective_date": "2025-01-01",
      "char_count": 600
    }
  },
  {
    "id": "admin_부당한_표시_또는_광고로_보지_아니하_0002",
    "text": ", 043-719-2181  제1조(목적) 이 고시는 「식품 등의 표시ᆞ광고에 관한 법률」제8조 및 같은 법 시행령 제3조제1항 별표 1 제3호나목\n에 따라 제품에 함유된 영양성분이나 원재료가 신체조직과 기능의 증진에 도움을 줄 수 있다는 내용으로써 부당\n한 표시 또는 광고로 보지 아니하는 표시ᆞ광고의 범위 및 요건을 정하여 부당한 표시 또는 광고로부터 소비자\n보호에 이바지함을 목적으로 한다.  제2조(정의) ① 이 고시에서 사용하는 용어의 뜻은 다음과 같다.\n1. \"원재료\"란 식품, 축산물, 식품첨가물(이하 \"식품등\"이라 한다)의 제조ᆞ가공에 사용되는 물질로서 최종 제품\n내에 들어있는 것을 말한다.\n2. \"성분\"이란 제품에 따로 첨가한 영양성분 또는 비영양성분이거나 원재료를 구성하는 단일물질로서 최종 제품\n에 함유되어 있는 것을 말한다.\n3. \"1일 섭취기준량\"이란 「건강기능식품의 기준 및 규격」 및 「건강기능식품 기능성 원료 및 기준ᆞ규격 인정에\n관한 규정」이 정하고 있는 건강기능식품 최종 제품 요건을 위한 일일섭취량 또는 기능성을 나타내기 위한 원\n재료 또는 성분의 하루 최소 섭취량을 말한다.\n② 이 고시에서 사용하는 용어 중 별도로 정하지 아니한 용어",
    "metadata": {
      "law": "부당한 표시 또는 광고로 보지 아니하는 식품등의 기능성 표시 또는 광고에 관한 규정",
      "law_number": "2024-62호",
      "category": "admin_rule",
      "chunk_index": 2,
      "total_chunks": 28,
      "effective_date": "2025-01-01",
      "char_count": 600
    }
  },
  {
    "id": "admin_부당한_표시_또는_광고로_보지_아니하_0003",
    "text": "격」 및 「건강기능식품 기능성 원료 및 기준ᆞ규격 인정에\n관한 규정」이 정하고 있는 건강기능식품 최종 제품 요건을 위한 일일섭취량 또는 기능성을 나타내기 위한 원\n재료 또는 성분의 하루 최소 섭취량을 말한다.\n② 이 고시에서 사용하는 용어 중 별도로 정하지 아니한 용어의 정의는 「식품등의 표시기준」, 「식품의 기준 및\n규격」, 「건강기능식품의 기준 및 규격」 및 「건강기능식품 기능성 원료 및 기준ᆞ규격 인정에 관한 규정」에 따른\n다.  제3조(적용범위) ① 이 고시는 「식품 등의 표시ᆞ광고에 관한 법률 시행령」별표 1 제3호나목에 따라 부당한 표시\n또는 광고로 보지 아니하는 \"신체조직과 기능의 증진에 도움을 줄 수 있다는 내용\"(이하 \"기능성\"이라 한다)을 표\n시 또는 광고하려는 식품등에 적용한다.\n② 제1항에도 불구하고 다음 각 호의 어느 하나에 해당하는 식품등은 제외한다.\n1. 「식품의 기준 및 규격」에서 정한 주류 및 특수의료용도등식품\n2. 별표 1의 영양성분 함량 기준에 적합하지 않은 식품등\n3. 36개월 이하 영유아를 섭취대상으로 하는 식품등 및 \"어린이\", \"아동\" 또는 이와 유사한 표현이나 이미지를 사\n용하여「아동복지법」제3조제1호에 따른 아동이",
    "metadata": {
      "law": "부당한 표시 또는 광고로 보지 아니하는 식품등의 기능성 표시 또는 광고에 관한 규정",
      "law_number": "2024-62호",
      "category": "admin_rule",
      "chunk_index": 3,
      "total_chunks": 28,
      "effective_date": "2025-01-01",
      "char_count": 600
    }
  },
  {
    "id": "admin_부당한_표시_또는_광고로_보지_아니하_0004",
    "text": "및 규격」에서 정한 주류 및 특수의료용도등식품\n2. 별표 1의 영양성분 함량 기준에 적합하지 않은 식품등\n3. 36개월 이하 영유아를 섭취대상으로 하는 식품등 및 \"어린이\", \"아동\" 또는 이와 유사한 표현이나 이미지를 사\n용하여「아동복지법」제3조제1호에 따른 아동이 섭취하는 것으로 표시 또는 광고한 식품등. 다만, 「어린이 식생\n활안전관리 특별법」 제14조제1항에 따라 품질인증을 받은 어린이 기호식품은 제외한다.\n4. 임산부 또는 수유중인 여성을 대상으로 한 식품등(임신 계획용 표방 식품등을 포함한다)\n5. 다음 각 목의 어느 하나에 해당하는 형태의 식품등\n가. 정제\n\n\n부당한 표시 또는 광고로 보지 아니하는 식품등의 기능성 표시 또는 광고에 관한 규정\n나. 캡슐\n다. 과립 또는 분말(이 경우 바로 섭취하는 스틱, 포 형태에 한함)\n라. 액상(이 경우 스프레이형ᆞ앰플형 및 이와 유사한 형태, 인삼ᆞ홍삼에 대한 기능성을 나타낸 농축액ᆞ100\nmL 이하 파우치 형태에 한함)  제4조(기능성의 범위) ① 이 고시의 기능성 범위는 다음 각 호와 같다.\n1. 「건강기능식품의 기준 및 규격」에서 기능성 원료로 정해진 것 중 별표 2 제1호에 해당하는 기능성\n2. 「",
    "metadata": {
      "law": "부당한 표시 또는 광고로 보지 아니하는 식품등의 기능성 표시 또는 광고에 관한 규정",
      "law_number": "2024-62호",
      "category": "admin_rule",
      "chunk_index": 4,
      "total_chunks": 28,
      "effective_date": "2025-01-01",
      "char_count": 599
    }
  },
  {
    "id": "admin_부당한_표시_또는_광고로_보지_아니하_0005",
    "text": "인삼ᆞ홍삼에 대한 기능성을 나타낸 농축액ᆞ100\nmL 이하 파우치 형태에 한함)  제4조(기능성의 범위) ① 이 고시의 기능성 범위는 다음 각 호와 같다.\n1. 「건강기능식품의 기준 및 규격」에서 기능성 원료로 정해진 것 중 별표 2 제1호에 해당하는 기능성\n2. 「건강기능식품 기능성 원료 및 기준ᆞ규격 인정에 관한 규정」제10조제1항에 따라 인정받은 기능성 원료의 제\n조자 또는 수입자가 별지 서식의 기능성을 나타내는 원재료의 일반식품 사용신청서로 식품의약품안전처장에\n게 신청하여 별표 2 제2호의 의사결정도에 따라 인정받은 원재료의 기능성\n3. 「식품등의 표시 또는 광고 실증에 관한 규정」제4조제3호 중 인체적용시험 또는 인체적용시험 결과에 대한 정\n성적 문헌고찰(체계적 고찰, SR: Systematic Review)을 통해 과학적 자료를 갖춘 다음 각 목에 해당하는 기능성\n가. 특정 영양성분의 대체, 제거 또는 감소로 인한 기능성\n나. 숙취해소와 관련된 기능성\n다. 「식품의 기준 및 규격」에 따른 발효유류에 대한 장건강ᆞ위건강 기능성\n② 제1항에도 불구하고 다음 각 호의 사항은 기능성에 해당하지 않는다.\n1. 어린이, 임산ᆞ수유부, 노인 등 건강민감 계층",
    "metadata": {
      "law": "부당한 표시 또는 광고로 보지 아니하는 식품등의 기능성 표시 또는 광고에 관한 규정",
      "law_number": "2024-62호",
      "category": "admin_rule",
      "chunk_index": 5,
      "total_chunks": 28,
      "effective_date": "2025-01-01",
      "char_count": 599
    }
  },
  {
    "id": "admin_부당한_표시_또는_광고로_보지_아니하_0006",
    "text": "의 대체, 제거 또는 감소로 인한 기능성\n나. 숙취해소와 관련된 기능성\n다. 「식품의 기준 및 규격」에 따른 발효유류에 대한 장건강ᆞ위건강 기능성\n② 제1항에도 불구하고 다음 각 호의 사항은 기능성에 해당하지 않는다.\n1. 어린이, 임산ᆞ수유부, 노인 등 건강민감 계층과 관련된 내용\n예 : 수험생 기억력개선, 어린이 키성장, 노인 인지능력개선\n2. 남성, 여성의 성기능 또는 생식기 건강과 관련된 내용\n예 : 정자운동성, 질건강\n3. 「건강기능식품의 기준 및 규격」의 질병발생 위험 감소 기능과 「건강기능식품 기능성 원료 및 기준ᆞ규격 인\n정에 관한 규정」제16조 관련 별표 4에서 정한 질병발생 위험 감소 기능에 대한 내용  제5조(식품등의 요건) ① 기능성 표시 또는 광고를 할 수 있는 식품등은 「식품위생법」제48조제3항에 따라 식품안\n전관리인증기준적용업소로 인증 받은 업소 또는 「축산물 위생관리법」제9조제3항에 따라 축산물 안전관리인증\n업소로 인증 받은 업소(이하 \"안전관리인증기준적용업소\"라 한다)에서 제조ᆞ가공되어야 한다. 다만, 「수입식품\n안전관리 특별법」제2조에 따른 수입식품등은 제외한다.\n② 제4조제1항제1호 및 제2호에 따른 기능성 표시 또는 광고를",
    "metadata": {
      "law": "부당한 표시 또는 광고로 보지 아니하는 식품등의 기능성 표시 또는 광고에 관한 규정",
      "law_number": "2024-62호",
      "category": "admin_rule",
      "chunk_index": 6,
      "total_chunks": 28,
      "effective_date": "2025-01-01",
      "char_count": 600
    }
  },
  {
    "id": "admin_부당한_표시_또는_광고로_보지_아니하_0007",
    "text": "법」제9조제3항에 따라 축산물 안전관리인증\n업소로 인증 받은 업소(이하 \"안전관리인증기준적용업소\"라 한다)에서 제조ᆞ가공되어야 한다. 다만, 「수입식품\n안전관리 특별법」제2조에 따른 수입식품등은 제외한다.\n② 제4조제1항제1호 및 제2호에 따른 기능성 표시 또는 광고를 할 수 있는 식품등에 함유된 기능성을 나타내는\n원재료 또는 성분의 요건은 다음 각호와 같다.\n1. 기능성을 나타내는 원재료 또는 성분의 함량은  별표 2 제1호에 따른 1일 섭취기준량 또는 제4조제1항제2호\n에 따라 식품원료로 사용 가능한 것으로 인정받은 기능성 원료의 1일 섭취기준량의 30% 이상을 충족하고 최\n대함량기준을 초과하지 않아야 한다. 이 경우 1일 섭취기준량 적용은 「식품등의 표시기준」에 따른 1회 섭취참\n고량을 기준으로 한다.\n2. 기능성을 나타내는 원재료 또는 성분은 「건강기능식품에 관한 법률」제4조 및 같은 법 제22조에 따른 우수건\n강기능식품제조기준 적용업소(이하 \"우수건강기능식품제조기준적용업소\"라 한다)에서 제조ᆞ가공된 것이어야\n한다. 다만, 「수입식품안전관리 특별법」제2조에 따른 수입식품등은 제외한다.\n\n\n부당한 표시 또는 광고로 보지 아니하는 식품등의 기능성 표시 또",
    "metadata": {
      "law": "부당한 표시 또는 광고로 보지 아니하는 식품등의 기능성 표시 또는 광고에 관한 규정",
      "law_number": "2024-62호",
      "category": "admin_rule",
      "chunk_index": 7,
      "total_chunks": 28,
      "effective_date": "2025-01-01",
      "char_count": 600
    }
  },
  {
    "id": "admin_부당한_표시_또는_광고로_보지_아니하_0008",
    "text": "제22조에 따른 우수건\n강기능식품제조기준 적용업소(이하 \"우수건강기능식품제조기준적용업소\"라 한다)에서 제조ᆞ가공된 것이어야\n한다. 다만, 「수입식품안전관리 특별법」제2조에 따른 수입식품등은 제외한다.\n\n\n부당한 표시 또는 광고로 보지 아니하는 식품등의 기능성 표시 또는 광고에 관한 규정\n③ 제4조제1항제3호에 따른 기능성 표시 또는 광고를 할 수 있는 식품등에 함유된 기능성을 나타내는 원재료 또\n는 성분의 요건은 다음 각 호와 같다.\n1. 기능성을 나타내는 원재료 또는 성분의 함량은 제4조제1항제3호에 따라 실증된 원재료 또는 성분의 함량을\n충족하거나, 실증된 최종제품의 원재료 또는 성분의 배합비율과 동일하게 제조되어야 한다.\n2. 기능성을 나타내는 원재료 또는 성분은 안전관리인증기준적용업소나 우수건강기능식품제조기준적용업소에서\n제조ᆞ가공된 것이어야 한다. 다만, 「수입식품안전관리 특별법」제2조에 따른 수입식품등은 제외한다.\n④ 기능성을 나타내는 원재료 또는 성분을 사용한 식품등은 다음 각 목의 어느 하나의 기준에 적합하여야 한다.\n이 경우 시험절차와 방법은「건강기능식품의 기준 및 규격」 또는 「건강기능식품 기능성 원료 및 기준ᆞ규격 인정\n에 관한 규정」에",
    "metadata": {
      "law": "부당한 표시 또는 광고로 보지 아니하는 식품등의 기능성 표시 또는 광고에 관한 규정",
      "law_number": "2024-62호",
      "category": "admin_rule",
      "chunk_index": 8,
      "total_chunks": 28,
      "effective_date": "2025-01-01",
      "char_count": 598
    }
  },
  {
    "id": "admin_부당한_표시_또는_광고로_보지_아니하_0009",
    "text": "에 따른 수입식품등은 제외한다.\n④ 기능성을 나타내는 원재료 또는 성분을 사용한 식품등은 다음 각 목의 어느 하나의 기준에 적합하여야 한다.\n이 경우 시험절차와 방법은「건강기능식품의 기준 및 규격」 또는 「건강기능식품 기능성 원료 및 기준ᆞ규격 인정\n에 관한 규정」에 따른다. 다만, 식품등의 특성상 기능성을 나타내는 성분의 표시량 시험방법을 적용하기 어려운\n경우에는 「식품등의 표시 또는 광고 실증에 관한 규정」제4조제3호가목에서 정하고 있는 시험절차와 방법에 적\n합하여야 한다.\n1. 「건강기능식품의 기준 및 규격」제 3. 개별 기준 및 규격 중 기능성분의 표시량 기준\n2. 「건강기능식품 기능성 원료 및 기준ᆞ규격 인정에 관한 규정」에 따라 인정된 기능성분 함량 기준 및 규격 중\n기능성분의 표시량 기준\n3. 제4조제1항제3호에 따라 실증된 기능성 성분 함량의 표시량 기준(실제 측정값은 표시량의 80% 이상이어야 한\n다) 또는 실증된 최종제품의 원재료 또는 성분의 배합비율과 동일\n⑤ 식품등에 함유된 기능성을 나타내는 원재료 또는 성분의 함량은 소비기한까지 유지되어야 하며, 제조일 또는\n수입일 기준으로 매 6개월 마다 제4항에 따른 기준에 적합하여야 한다.  제5",
    "metadata": {
      "law": "부당한 표시 또는 광고로 보지 아니하는 식품등의 기능성 표시 또는 광고에 관한 규정",
      "law_number": "2024-62호",
      "category": "admin_rule",
      "chunk_index": 9,
      "total_chunks": 28,
      "effective_date": "2025-01-01",
      "char_count": 600
    }
  },
  {
    "id": "admin_부당한_표시_또는_광고로_보지_아니하_0010",
    "text": "0% 이상이어야 한\n다) 또는 실증된 최종제품의 원재료 또는 성분의 배합비율과 동일\n⑤ 식품등에 함유된 기능성을 나타내는 원재료 또는 성분의 함량은 소비기한까지 유지되어야 하며, 제조일 또는\n수입일 기준으로 매 6개월 마다 제4항에 따른 기준에 적합하여야 한다.  제5조의2(기준의 적용) 이 고시와 관련된 기준 및 규격 등의 내용으로 「건강기능식품의 기준 및 규격」 또는 「식품\n등의 표시기준」에 변경된 사항이 있는 경우에는 변경된 사항을 우선 적용한다.  제6조(표시 또는 광고의 방법) ① 제4조제1항제1호 및 제2호에 따른 기능성을 표시하려는 식품등은 다음 각 호의\n사항을 포함하여야 한다. 이 경우 제1호 및 제5호의 사항은 주표시면에 표시하여야 하고, 그 이외의 사항은 기능\n성 표시 서식 도안을 활용하여 표시할 수 있다.\n1. 기능성에 도움을 줄 수 있다고 알려진 또는 보고된 기능성 원재료 또는 성분이 식품등에 들어있다는 내용\n예 : 본 제품에는 A(기능성)에 도움을 줄 수 있다고 알려진(또는 보고된) B(기능성 원재료 또는 성분)가 들어 있습니다.\n2. 기능성 성분 함량. 이 경우 기능성 성분 함량 표시 단위는 「식품등의 표시기준」 별지 1. 1. 아.",
    "metadata": {
      "law": "부당한 표시 또는 광고로 보지 아니하는 식품등의 기능성 표시 또는 광고에 관한 규정",
      "law_number": "2024-62호",
      "category": "admin_rule",
      "chunk_index": 10,
      "total_chunks": 28,
      "effective_date": "2025-01-01",
      "char_count": 600
    }
  },
  {
    "id": "admin_부당한_표시_또는_광고로_보지_아니하_0011",
    "text": "또는 성분이 식품등에 들어있다는 내용\n예 : 본 제품에는 A(기능성)에 도움을 줄 수 있다고 알려진(또는 보고된) B(기능성 원재료 또는 성분)가 들어 있습니다.\n2. 기능성 성분 함량. 이 경우 기능성 성분 함량 표시 단위는 「식품등의 표시기준」 별지 1. 1. 아. 1)에 따른 영양\n성분 표시단위 기준을 준용한다.\n3. 1일 섭취기준량\n4. 섭취 시 주의사항. 이 경우 해당 기능성을 나타내는 원재료 또는 성분별로 「건강기능식품의 기준 및 규격」과\n「건강기능식품 기능성 원료 및 기준ᆞ규격 인정에 관한 규정」에서 정한 사항을 모두 포함하여야 하며, 섭취 시\n주의사항을 정하고 있지 아니하는 경우 표시를 생략할 수 있다.\n5. \"본 제품은 건강기능식품이 아닙니다.\"라는 문구\n6. 질병의 예방ᆞ치료를 위한 제품이 아니라는 문구\n7. 균형잡힌 식생활을 권장하는 문구\n\n\n부당한 표시 또는 광고로 보지 아니하는 식품등의 기능성 표시 또는 광고에 관한 규정\n8. 이상사례가 있는 경우 섭취를 중지하고 전문가와 상담이 필요하다는 문구\n② 제4조제1항제3호에 따른 기능성을 표시하려는 식품등은 다음 각 호의 사항을 포함하여야 한다. 이 경우 제\n1호 및 제5호의 사항은 주표시면",
    "metadata": {
      "law": "부당한 표시 또는 광고로 보지 아니하는 식품등의 기능성 표시 또는 광고에 관한 규정",
      "law_number": "2024-62호",
      "category": "admin_rule",
      "chunk_index": 11,
      "total_chunks": 28,
      "effective_date": "2025-01-01",
      "char_count": 600
    }
  },
  {
    "id": "admin_부당한_표시_또는_광고로_보지_아니하_0012",
    "text": "니하는 식품등의 기능성 표시 또는 광고에 관한 규정\n8. 이상사례가 있는 경우 섭취를 중지하고 전문가와 상담이 필요하다는 문구\n② 제4조제1항제3호에 따른 기능성을 표시하려는 식품등은 다음 각 호의 사항을 포함하여야 한다. 이 경우 제\n1호 및 제5호의 사항은 주표시면에 표시하여야 하고, 그 이외의 사항은 기능성 표시 서식 도안을 활용하여 표시\n할 수 있다.\n1. 제4조제1항제3호에 해당하는 기능성 내용\n예 : ‘숙취해소’ 라는 내용\n2. 기능성 성분 함량(최종제품으로 실증한 경우에는 제외). 이 경우 기능성 성분 함량 표시 단위는 「식품등의 표\n시기준」 별지 1. 1. 아. 1)에 따른 영양성분 표시단위 기준을 준용한다.\n3. 1일 섭취기준량\n4. \"과도한 음주는 건강을 해칩니다.\"라는 문구(제4조제1항제3호나목의 기능성을 표시하려는 식품등의 경우에만\n해당한다)\n5. \"본 제품은 건강기능식품이 아닙니다.\"라는 문구\n6. 질병의 예방ᆞ치료를 위한 제품이 아니라는 문구\n7. 이상사례가 있는 경우 섭취를 중지하고 전문가와 상담이 필요하다는 문구\n③ 제1항 또는 제2항에 따른 표시가 있는 식품등에 한하여 기능성 광고를 할 수 있다. 이 경우 \"본 제품은 건강기\n능",
    "metadata": {
      "law": "부당한 표시 또는 광고로 보지 아니하는 식품등의 기능성 표시 또는 광고에 관한 규정",
      "law_number": "2024-62호",
      "category": "admin_rule",
      "chunk_index": 12,
      "total_chunks": 28,
      "effective_date": "2025-01-01",
      "char_count": 600
    }
  },
  {
    "id": "admin_부당한_표시_또는_광고로_보지_아니하_0013",
    "text": "아닙니다.\"라는 문구\n6. 질병의 예방ᆞ치료를 위한 제품이 아니라는 문구\n7. 이상사례가 있는 경우 섭취를 중지하고 전문가와 상담이 필요하다는 문구\n③ 제1항 또는 제2항에 따른 표시가 있는 식품등에 한하여 기능성 광고를 할 수 있다. 이 경우 \"본 제품은 건강기\n능식품이 아닙니다.\"라는 문구를 포함하여야 한다.  제7조(자료 공개 등) 제6조에 따른 표시 또는 광고를 하려는 영업자는 「식품위생법」제64조에 따른 한국식품산업협\n회의 인터넷 홈페이지에 다음 각 호의 자료를 공개하여야 한다.\n1. 제품명\n2. 업소명\n3. 기능성 성분명과 그 함량\n4. 1일 섭취기준량 및 기능성 성분 함량의 1일 섭취기준량에 대한 비율(제6조제2항에 따른 경우는 제외)\n5. 기능성 표시 내용\n6. 과학적 근거자료  제8조(재검토 기한) 식품의약품안전처장은「훈령ᆞ예규 등의 발령 및 관리에 관한 규정」에 따라 2021년 1월 1일을\n기준으로 매 3년이 되는 시점(매 3년째의 12월 31일까지를 말한다)마다 그 타당성을 검토하여 개선 등의 조치를\n하여야 한다.  부칙 <제2024-62호,2024.10.17.>\n제1조(시행일) 이 고시는 2025년 1월 1일부터 시행한다. 다만, 별표",
    "metadata": {
      "law": "부당한 표시 또는 광고로 보지 아니하는 식품등의 기능성 표시 또는 광고에 관한 규정",
      "law_number": "2024-62호",
      "category": "admin_rule",
      "chunk_index": 13,
      "total_chunks": 28,
      "effective_date": "2025-01-01",
      "char_count": 599
    }
  },
  {
    "id": "admin_부당한_표시_또는_광고로_보지_아니하_0014",
    "text": "년 1월 1일을\n기준으로 매 3년이 되는 시점(매 3년째의 12월 31일까지를 말한다)마다 그 타당성을 검토하여 개선 등의 조치를\n하여야 한다.  부칙 <제2024-62호,2024.10.17.>\n제1조(시행일) 이 고시는 2025년 1월 1일부터 시행한다. 다만, 별표 1의 제2호나목은 고시한 날부터 시행한다.\n제2조(적용례) 이 고시 시행 후 최초로 제조ᆞ가공 또는 수입(선적일을 기준으로 한다)한 식품부터 적용한다. 다만,\n이 고시 시행 전에 이미 제조ᆞ가공 또는 수입된 식품이 이 고시를 적용받고자 하는 경우 이 고시를 적용할 수\n있다.\n\n\n부당한 표시 또는 광고로 보지 아니하는 식품등의 기능성 표시 또는 광고에 관한 규정\n제3조(제6조제2항에 관한 경과조치) 제4조제1항제3호나목에 따라 숙취해소와 관련된 기능성을 표시ᆞ광고하는 경\n우 제6조제2항의 규정에도 불구하고 이 고시 시행 당시 종전의 규정에 따라 이미 제조ᆞ가공 또는 수입(선적일\n을 기준으로 한다)된 식품등은 해당 식품등의 소비기한까지 종전의 표시 또는 광고의 방법을 사용할 수 있다.  [별표 1] 기능성 표시 식품등의 영양성분 함량 기준(제3조제2항제2호 관련)  [별표 2] 기능성 범위(제4조",
    "metadata": {
      "law": "부당한 표시 또는 광고로 보지 아니하는 식품등의 기능성 표시 또는 광고에 관한 규정",
      "law_number": "2024-62호",
      "category": "admin_rule",
      "chunk_index": 14,
      "total_chunks": 28,
      "effective_date": "2025-01-01",
      "char_count": 600
    }
  },
  {
    "id": "admin_부당한_표시_또는_광고로_보지_아니하_0015",
    "text": "규정에 따라 이미 제조ᆞ가공 또는 수입(선적일\n을 기준으로 한다)된 식품등은 해당 식품등의 소비기한까지 종전의 표시 또는 광고의 방법을 사용할 수 있다.  [별표 1] 기능성 표시 식품등의 영양성분 함량 기준(제3조제2항제2호 관련)  [별표 2] 기능성 범위(제4조제1항 관련)  [별지] 기능성을 나타내는 원재료의 일반식품 사용 신청서  [별도] 기능성 표시 서식 도안(제6조제1항 관련)  [별표1]기능성표시식품등의영양성분함량기준(제3조제2항제2\n호관련)\n1.공통기준\n가.식품유형별로각영양성분의함량기준에적합하여야한다.\n나.식품별영양성분함량기준은「식품등의표시기준」에따른해당\n식품의1회섭취참고량을기준단위로한다.다만,1회섭취참고량\n이30g이하이면50g(mL)으로하고,1회섭취참고량이없는경\n우와식용유지류중트랜스지방의경우는100g(mL)으로한다.\n구 분\n영양성분\n｢식품의 기준 및 규격｣에 따른 식품유형\n①\n일반식품\n②\n농축과채즙,\n과채주스\n③\n김치류,\n장류 \n④\n식용유지류\n⑤\n소스,\n마요네즈\n⑥\n우유,\n가공유\n⑦\n치즈\n⑧\n초콜릿\n총지방\n10.0g\n이하\n10.0g\n이하\n10.0g\n이하\n--\n10.0g\n이하\n15.0g\n이하\n-\n포화지방\n3.0g\n이하\n3.0g\n이하\n3.0g",
    "metadata": {
      "law": "부당한 표시 또는 광고로 보지 아니하는 식품등의 기능성 표시 또는 광고에 관한 규정",
      "law_number": "2024-62호",
      "category": "admin_rule",
      "chunk_index": 15,
      "total_chunks": 28,
      "effective_date": "2025-01-01",
      "char_count": 599
    }
  },
  {
    "id": "admin_부당한_표시_또는_광고로_보지_아니하_0016",
    "text": "일반식품\n②\n농축과채즙,\n과채주스\n③\n김치류,\n장류 \n④\n식용유지류\n⑤\n소스,\n마요네즈\n⑥\n우유,\n가공유\n⑦\n치즈\n⑧\n초콜릿\n총지방\n10.0g\n이하\n10.0g\n이하\n10.0g\n이하\n--\n10.0g\n이하\n15.0g\n이하\n-\n포화지방\n3.0g\n이하\n3.0g\n이하\n3.0g\n이하\n20.0g\n이하\n3.0g\n이하\n5.0g\n이하\n10.0g\n이하\n-\n트랜스지방\n0.2g\n이하\n0.2g\n이하\n0.2g\n이하\n2.0g\n이하\n0.2g\n이하\n0.5g\n이하\n0.8g\n이하\n0.2g\n이하\n당류\n20.0g\n이하\n26.0g\n이하\n20.0g\n이하\n20.0g\n이하\n20.0g\n이하\n20.0g\n이하\n20.0g\n이하\n20.0g\n이하\n나트륨\n400.0mg\n이하\n400.0mg\n이하\n-\n400.0mg\n이하\n400.0mg\n이하\n400.0mg\n이하\n400.0mg\n이하\n400.0mg\n이하\n주)①일반식품:｢식품의기준및규격｣으로관리하고있는가공식품\n중②～⑧을제외한가공식품\n2.개별기준\n가.원재료또는성분별기능성을표시또는광고하려는식품등은\n다음의영양성분‘저’표시기준에충족하여야한다.이경우‘저’\n표시기준은「식품등의표시기준」영양성분함량강조표시기준에\n적합하여야한다.\n연번\n기능성 원재료 \n또는 성분\n기능성영양성분 개별 기준\n1인삼",
    "metadata": {
      "law": "부당한 표시 또는 광고로 보지 아니하는 식품등의 기능성 표시 또는 광고에 관한 규정",
      "law_number": "2024-62호",
      "category": "admin_rule",
      "chunk_index": 16,
      "total_chunks": 28,
      "effective_date": "2025-01-01",
      "char_count": 599
    }
  },
  {
    "id": "admin_부당한_표시_또는_광고로_보지_아니하_0017",
    "text": "②～⑧을제외한가공식품\n2.개별기준\n가.원재료또는성분별기능성을표시또는광고하려는식품등은\n다음의영양성분‘저’표시기준에충족하여야한다.이경우‘저’\n표시기준은「식품등의표시기준」영양성분함량강조표시기준에\n적합하여야한다.\n연번\n기능성 원재료 \n또는 성분\n기능성영양성분 개별 기준\n1인삼\n면역력증진·피로·뼈건강개선에도움을줄\n수있음\n-\n2홍삼면역력증진·피로개선·항산화·갱년기여-\n\n연번\n기능성 원재료 \n또는 성분\n기능성영양성분 개별 기준\n성의건강에도움을줄수있음\n혈소판응집억제를통한혈액흐름에도\n움을줄수있음\n저 포화지방,\n저 트랜스지방\n3클로렐라\n피부건강·항산화·면역력증진에도움을줄\n수있음\n-\n혈중콜레스테롤개선에도움을줄수있음\n저 포화지방,\n저 트랜스지방\n4스피루리나\n피부건강·항산화에도움을줄수있음-\n혈중콜레스테롤개선에도움을줄수있음\n저 포화지방,\n저 트랜스지방\n5\n프로폴리스 \n추출물\n항산화·구강에서의항균작용에도움을줄\n수있음\n※구강항균작용은구강에직접접촉할수\n있는형태에한하며,섭취량을적용하지않음\n저 당류 \n6\n구아바잎 \n추출물\n식후혈당상승억제에도움을줄수있음저 당류 \n7\n바나바잎 \n추출물\n식후혈당상승억제에도움을줄수있음저 당류 \n8\nEPA및 DHA\n함유 유지\n혈중중성지질개선·혈행개선에도움을\n줄수있음",
    "metadata": {
      "law": "부당한 표시 또는 광고로 보지 아니하는 식품등의 기능성 표시 또는 광고에 관한 규정",
      "law_number": "2024-62호",
      "category": "admin_rule",
      "chunk_index": 17,
      "total_chunks": 28,
      "effective_date": "2025-01-01",
      "char_count": 599
    }
  },
  {
    "id": "admin_부당한_표시_또는_광고로_보지_아니하_0018",
    "text": "강항균작용은구강에직접접촉할수\n있는형태에한하며,섭취량을적용하지않음\n저 당류 \n6\n구아바잎 \n추출물\n식후혈당상승억제에도움을줄수있음저 당류 \n7\n바나바잎 \n추출물\n식후혈당상승억제에도움을줄수있음저 당류 \n8\nEPA및 DHA\n함유 유지\n혈중중성지질개선·혈행개선에도움을\n줄수있음\n저 포화지방,\n저 트랜스지방\n건조한눈을개선하여눈건강에도움을\n줄수있음\n-\n9매실추출물피로개선에도움을줄수있음-\n10\n구아검/구아검\n가수분해물\n혈중콜레스테롤개선에도움을줄수있음\n저 포화지방,\n저 트랜스지방\n식후혈당상승억제에도움을줄수있음저 당류\n장내유익균증식·배변활동원활에도움을\n줄수있음\n-\n11\n난소화성말토\n덱스트린\n식후혈당상승억제에도움을줄수있음저 당류\n혈중중성지질개선에도움을줄수있음\n저 포화지방,\n저 트랜스지방\n배변활동원활에도움을줄수있음-\n12대두식이섬유\n혈중콜레스테롤개선에도움을줄수있음\n저 포화지방,\n저 트랜스지방\n식후혈당상승억제에도움을줄수있음저 당류\n배변활동원활에도움을줄수있음-\n13\n목이버섯\n식이섬유\n배변활동원활에도움을줄수있음-\n14밀식이섬유\n식후혈당상승억제에도움을줄수있음저 당류\n배변활동원활에도움을줄수있음-\n15보리식이섬유배변활동원활에도움을줄수있음-\n16\n옥수수겨\n식이섬유\n혈중콜레스테롤개선에도움을줄수있",
    "metadata": {
      "law": "부당한 표시 또는 광고로 보지 아니하는 식품등의 기능성 표시 또는 광고에 관한 규정",
      "law_number": "2024-62호",
      "category": "admin_rule",
      "chunk_index": 18,
      "total_chunks": 28,
      "effective_date": "2025-01-01",
      "char_count": 600
    }
  },
  {
    "id": "admin_부당한_표시_또는_광고로_보지_아니하_0019",
    "text": "있음저 당류\n배변활동원활에도움을줄수있음-\n13\n목이버섯\n식이섬유\n배변활동원활에도움을줄수있음-\n14밀식이섬유\n식후혈당상승억제에도움을줄수있음저 당류\n배변활동원활에도움을줄수있음-\n15보리식이섬유배변활동원활에도움을줄수있음-\n16\n옥수수겨\n식이섬유\n혈중콜레스테롤개선에도움을줄수있음\n저 포화지방,\n저 트랜스지방\n식후혈당상승억제에도움을줄수있음저 당류\n17이눌린/혈중콜레스테롤개선에도움을줄수있음저 포화지방,\n\n나.제4조제1항제2호에따라식품의약품안전처장에게신청하여인정받\n은원재료의기능성을표시또는광고하려는식품등은통보받은\n영양성분함량강조표시개별기준에적합하여야한다.\n연번\n기능성 원재료 \n또는 성분\n기능성영양성분 개별 기준\n치커리추출물\n저 트랜스지방\n식후혈당상승억제에도움을줄수있음저 당류\n배변활동원활에도움을줄수있음-\n18\n차전자피\n식이섬유\n혈중콜레스테롤개선에도움을줄수있음\n저 포화지방,\n저 트랜스지방\n배변활동원활에도움을줄수있음-\n19\n호로파종자\n식이섬유\n식후혈당상승억제에도움을줄수있음저 당류 \n20알로에 겔\n피부건강·장건강·면역력증진에도움을줄수\n있음\n-\n21프락토올리고당\n장내유익균증식및배변활동원활에도\n움을줄수있음\n-\n22프로바이오틱스\n유산균증식및유해균억제·배변활동원활·\n장건강에도움을줄수있음",
    "metadata": {
      "law": "부당한 표시 또는 광고로 보지 아니하는 식품등의 기능성 표시 또는 광고에 관한 규정",
      "law_number": "2024-62호",
      "category": "admin_rule",
      "chunk_index": 19,
      "total_chunks": 28,
      "effective_date": "2025-01-01",
      "char_count": 599
    }
  },
  {
    "id": "admin_부당한_표시_또는_광고로_보지_아니하_0020",
    "text": "-\n19\n호로파종자\n식이섬유\n식후혈당상승억제에도움을줄수있음저 당류 \n20알로에 겔\n피부건강·장건강·면역력증진에도움을줄수\n있음\n-\n21프락토올리고당\n장내유익균증식및배변활동원활에도\n움을줄수있음\n-\n22프로바이오틱스\n유산균증식및유해균억제·배변활동원활·\n장건강에도움을줄수있음\n-\n23홍국혈중콜레스테롤개선에도움을줄수있음\n저 포화지방,\n저 트랜스지방\n24대두단백\n혈중콜레스테롤개선에도움을줄수\n있음\n저 포화지방,\n저 트랜스지방\n25\n폴리감마\n글루탐산\n체내칼슘흡수촉진에도움을줄수있음-\n26마늘혈중콜레스테롤개선에도움을줄수있음\n저 포화지방,\n저 트랜스지방\n27라피노스\n장내유익균의증식과유해균의억제도움\n을줄수있음\n배변활동을원활히하는데도움을줄수\n있음\n-\n28분말한천배변활동에도움을줄수있음-\n29\n유단백\n가수분해물\n스트레스로인한긴장완화에도움을줄\n수있음\n-\n\n[별표2]기능성범위(제4조제1항관련)\n1.기능성원재료또는성분별기능성및1일섭취기준량\n순\n번\n기능성원재료\n또는성분\n기능성1일섭취기준량\n1인삼\n면역력증진·피로개선에도\n움을줄수있음\n•진세노사이드Rg1과Rb1의합계로\n서3∼80mg\n뼈건강에도움을줄수있\n음\n•진세노사이드Rg1과Rb1의합계로\n서25mg\n2홍삼\n면역력증진·피로개선에\n도움을줄수있음\n•진세",
    "metadata": {
      "law": "부당한 표시 또는 광고로 보지 아니하는 식품등의 기능성 표시 또는 광고에 관한 규정",
      "law_number": "2024-62호",
      "category": "admin_rule",
      "chunk_index": 20,
      "total_chunks": 28,
      "effective_date": "2025-01-01",
      "char_count": 600
    }
  },
  {
    "id": "admin_부당한_표시_또는_광고로_보지_아니하_0021",
    "text": "일섭취기준량\n순\n번\n기능성원재료\n또는성분\n기능성1일섭취기준량\n1인삼\n면역력증진·피로개선에도\n움을줄수있음\n•진세노사이드Rg1과Rb1의합계로\n서3∼80mg\n뼈건강에도움을줄수있\n음\n•진세노사이드Rg1과Rb1의합계로\n서25mg\n2홍삼\n면역력증진·피로개선에\n도움을줄수있음\n•진세노사이드Rg1,Rb1및Rg3의\n합계로서3∼80mg\n혈소판응집억제를통한\n혈액흐름·항산화에도움을\n줄수있음\n•진세노사이드Rg1,Rb1및Rg3의\n합계로서2.4∼80mg\n갱년기여성의건강에도\n움을줄수있음\n•진세노사이드Rg1,Rb1및Rg3의\n합계로서25∼80mg\n3클로렐라\n피부건강·항산화에도움을\n줄수있음\n•총엽록소로서8〜150mg\n면역력증진·혈중콜레스테롤\n개선에도움을줄수있음\n•총엽록소로서125〜150mg\n4스피루리나\n피부건강·항산화에도움을\n줄수있음\n•총엽록소로서8～150mg\n혈중콜레스테롤개선에도움\n을줄수있음\n•총엽록소로서40～150mg\n5\n프로폴리스\n추출물\n항산화·구강에서의항균작\n용에도움을줄수있음\n※구강항균작용은구강에\n직접접촉할수있는형태\n에한하며,섭취량을적용하\n지않음\n•총플라보노이드로서16～17mg\n6\n구아바잎\n추출물\n식후혈당상승억제에도\n움을줄수있음\n•총폴리페놀로서120mg\n7\n바나바잎\n추출물\n식후혈당상승억",
    "metadata": {
      "law": "부당한 표시 또는 광고로 보지 아니하는 식품등의 기능성 표시 또는 광고에 관한 규정",
      "law_number": "2024-62호",
      "category": "admin_rule",
      "chunk_index": 21,
      "total_chunks": 28,
      "effective_date": "2025-01-01",
      "char_count": 600
    }
  },
  {
    "id": "admin_부당한_표시_또는_광고로_보지_아니하_0022",
    "text": "폴리스\n추출물\n항산화·구강에서의항균작\n용에도움을줄수있음\n※구강항균작용은구강에\n직접접촉할수있는형태\n에한하며,섭취량을적용하\n지않음\n•총플라보노이드로서16～17mg\n6\n구아바잎\n추출물\n식후혈당상승억제에도\n움을줄수있음\n•총폴리페놀로서120mg\n7\n바나바잎\n추출물\n식후혈당상승억제에도\n움을줄수있음\n•코로솔산으로서0.45～1.3mg\n8\nEPA및DHA\n함유유지\n혈중중성지질개선·혈행\n개선에도움을줄수있음\n•EPA와DHA의합으로서0.5～2g\n건조한눈을개선하여눈\n건강에도움을줄수있음\n•EPA와DHA의합으로서0.6～1g\n9매실추출물\n피로개선에도움을줄\n수있음\n•구연산으로서1～1.3g\n10\n구아검/구아검\n가수분해물\n혈중콜레스테롤개선.식\n후혈당상승억제.배변활\n•구아검/구아검가수분해물식이섬유\n로서9.9～27g\n\n순\n번\n기능성원재료\n또는성분\n기능성1일섭취기준량\n동원활에도움을줄수있\n음\n장내유익균증식에도움\n을줄수있음\n•구아검/구아검가수분해물식이섬유\n로서4.6～27g\n11\n난소화성말토덱\n스트린\n식후혈당상승억제에도\n움을줄수있음\n•난소화성말토덱스트린식이섬유로서\n4.0～30g(액상원료는4.0～44g)\n혈중중성지질개선에도\n움을줄수있음\n•난소화성말토덱스트린식이섬유로서\n5.0～30g(액상원료는5.0～44g)",
    "metadata": {
      "law": "부당한 표시 또는 광고로 보지 아니하는 식품등의 기능성 표시 또는 광고에 관한 규정",
      "law_number": "2024-62호",
      "category": "admin_rule",
      "chunk_index": 22,
      "total_chunks": 28,
      "effective_date": "2025-01-01",
      "char_count": 600
    }
  },
  {
    "id": "admin_부당한_표시_또는_광고로_보지_아니하_0023",
    "text": "가수분해물식이섬유\n로서4.6～27g\n11\n난소화성말토덱\n스트린\n식후혈당상승억제에도\n움을줄수있음\n•난소화성말토덱스트린식이섬유로서\n4.0～30g(액상원료는4.0～44g)\n혈중중성지질개선에도\n움을줄수있음\n•난소화성말토덱스트린식이섬유로서\n5.0～30g(액상원료는5.0～44g)\n배변활동원활에도움을\n줄수있음\n•난소화성말토덱스트린식이섬유로서\n4.2～30g(액상원료는4.2～44g)\n12대두식이섬유\n혈중콜레스테롤개선·배변\n활동원활에도움을줄수\n있음\n•대두식이섬유로서20～60g\n식후혈당상승억제에도\n움을줄수있음\n•대두식이섬유로서10～60g\n13\n목이버섯\n식이섬유\n배변활동원활에도움을줄\n수있음\n•목이버섯식이섬유로서12g\n14밀식이섬유\n식후혈당상승억제에도\n움을줄수있음\n•밀식이섬유로서6～36g\n배변활동원활에도움을줄\n수있음\n•밀식이섬유로서36g\n15보리식이섬유\n배변활동원활에도움을줄\n수있음\n•보리식이섬유로서20～25g\n16\n옥수수겨\n식이섬유\n혈중콜레스테롤개선·식후\n혈당상승억제에도움을\n줄수있음\n•옥수수겨식이섬유로서10g\n17\n이눌린/\n치커리추출물\n혈중콜레스테롤개선,식\n후혈당상승억제에도움\n을줄수있음\n•이눌린/치커리추출물식이섬유로서\n7.2～20g\n배변활동원활에도움을\n줄수있음\n•이눌린/치커리추출물",
    "metadata": {
      "law": "부당한 표시 또는 광고로 보지 아니하는 식품등의 기능성 표시 또는 광고에 관한 규정",
      "law_number": "2024-62호",
      "category": "admin_rule",
      "chunk_index": 23,
      "total_chunks": 28,
      "effective_date": "2025-01-01",
      "char_count": 600
    }
  },
  {
    "id": "admin_부당한_표시_또는_광고로_보지_아니하_0024",
    "text": "수수겨\n식이섬유\n혈중콜레스테롤개선·식후\n혈당상승억제에도움을\n줄수있음\n•옥수수겨식이섬유로서10g\n17\n이눌린/\n치커리추출물\n혈중콜레스테롤개선,식\n후혈당상승억제에도움\n을줄수있음\n•이눌린/치커리추출물식이섬유로서\n7.2～20g\n배변활동원활에도움을\n줄수있음\n•이눌린/치커리추출물식이섬유로서\n6.4～20g\n18\n차전자피\n식이섬유\n혈중콜레스테롤개선에도\n움을줄수있음\n•차전자피식이섬유로서5.5g이상\n배변활동원활에도움을줄\n수있음\n•차전자피식이섬유로서3.9g이상\n19\n호로파종자\n식이섬유\n식후혈당상승억제에도\n움을줄수있음\n•호로파종자식이섬유로서12～50g\n20알로에겔\n피부건강·장건강·면역력증진\n에도움을줄수있음\n•총다당체함량으로서100～420mg\n\n2.의사결정도\n순\n번\n기능성원재료\n또는성분\n기능성1일섭취기준량\n21\n프락토\n올리고당\n장내유익균증식및배변\n활동원활에도움을줄\n수있음\n•프락토올리고당으로서3～8g\n22프로바이오틱스\n유산균증식및유해균억\n제·배변활동원활·장건강\n에도움을줄수있음.\n•100,000,000CFU\n23홍국\n혈중콜레스테롤개선에도\n움을줄수있음\n•총모나콜린K로서4～8mg\n24대두단백\n혈중콜레스테롤개선에\n도움을줄수있음\n•대두단백으로서15g이상\n25\n폴리감마\n글루탐산\n체내칼슘흡수촉진",
    "metadata": {
      "law": "부당한 표시 또는 광고로 보지 아니하는 식품등의 기능성 표시 또는 광고에 관한 규정",
      "law_number": "2024-62호",
      "category": "admin_rule",
      "chunk_index": 24,
      "total_chunks": 28,
      "effective_date": "2025-01-01",
      "char_count": 600
    }
  },
  {
    "id": "admin_부당한_표시_또는_광고로_보지_아니하_0025",
    "text": "유산균증식및유해균억\n제·배변활동원활·장건강\n에도움을줄수있음.\n•100,000,000CFU\n23홍국\n혈중콜레스테롤개선에도\n움을줄수있음\n•총모나콜린K로서4～8mg\n24대두단백\n혈중콜레스테롤개선에\n도움을줄수있음\n•대두단백으로서15g이상\n25\n폴리감마\n글루탐산\n체내칼슘흡수촉진에도\n움을줄수있음\n•폴리감마글루탐산으로서60～70mg\n26마늘\n혈중콜레스테롤개선에도움\n을줄수있음\n•마늘분말로서0.6∼1.0g\n27라피노스\n장내유익균의증식과유\n해균의억제도움을줄수\n있음,배변활동을원활히\n하는데도움을줄수있음\n•라피노스로서3～5g\n28분말한천\n배변활동에도움을줄수\n있음\n•분말한천으로서2～5g\n(총식이섬유로서1.6～4.0g)\n29\n유단백가수\n분해물\n스트레스로인한긴장완\n화에도움을줄수있음\n•유단백가수분해물로서150mg\n(알파에스1카제인(α\nS1\n-casein)\n(f91-100)\n으로서\n2.7～4.1mg)  ■ 부당한 표시 또는 광고로 보지 아니하는 식품등의 기능성 표시 또는 광고에 관한 규정[별지 서식] \n기능성을나타내는원재료의일반식품사용신청서\n※ 색상이 어두운 난은 신청인이 작성하지 않습니다.\n접수번호접수일시발급일처리기간 \n60일\n신청인\n성명(법인은 법인 명칭 및 \n대표자의 성명)\n업체명(기",
    "metadata": {
      "law": "부당한 표시 또는 광고로 보지 아니하는 식품등의 기능성 표시 또는 광고에 관한 규정",
      "law_number": "2024-62호",
      "category": "admin_rule",
      "chunk_index": 25,
      "total_chunks": 28,
      "effective_date": "2025-01-01",
      "char_count": 600
    }
  },
  {
    "id": "admin_부당한_표시_또는_광고로_보지_아니하_0026",
    "text": "고로 보지 아니하는 식품등의 기능성 표시 또는 광고에 관한 규정[별지 서식] \n기능성을나타내는원재료의일반식품사용신청서\n※ 색상이 어두운 난은 신청인이 작성하지 않습니다.\n접수번호접수일시발급일처리기간 \n60일\n신청인\n성명(법인은 법인 명칭 및 \n대표자의 성명)\n업체명(기관명)영업의 종류\n허가/신고/등록번호\n소재지(주소)\n(전화번호)\n수입건강\n기능식품\n수출국\n제조회사\n소재지\n신청사항\n기능성 원료 인정 번호\n기능성 원재료\n「부당한 표시.광고로 보지 아니하는 식품등의 기능성 표시.광고에 관한 규정」 제4조제1항제2호에 \n따라 기능성 원료의 일반식품 사용을 신청합니다.  년  월  일  신청인  (서명 또는 인)\n식품의약품안전처장\n귀하\n신청인\n제출서류\n 건강기능식품 기능성 원료 인정서\n행정정보 공동이용 동의서\n 본인은 이 건 업무처리와 관련하여 담당 공무원이 「전자정부법」 제36조에 따른 행정정보의 공동이용을 통하여 위의 담당 공\n무원 확인 사항을 확인하는 것에 동의합니다. * 동의하지 않는 경우에는 신청인이 직접 관련 서류를 제출해야 합니다.\n신청인\n(서명 또는 인)\n유의사항  「식품의 기준 및 규격」에 적합한 원재료 또는 성분에 한하여 신청이 가능합니다.\n처리절차",
    "metadata": {
      "law": "부당한 표시 또는 광고로 보지 아니하는 식품등의 기능성 표시 또는 광고에 관한 규정",
      "law_number": "2024-62호",
      "category": "admin_rule",
      "chunk_index": 26,
      "total_chunks": 28,
      "effective_date": "2025-01-01",
      "char_count": 600
    }
  },
  {
    "id": "admin_부당한_표시_또는_광고로_보지_아니하_0027",
    "text": "이용을 통하여 위의 담당 공\n무원 확인 사항을 확인하는 것에 동의합니다. * 동의하지 않는 경우에는 신청인이 직접 관련 서류를 제출해야 합니다.\n신청인\n(서명 또는 인)\n유의사항  「식품의 기준 및 규격」에 적합한 원재료 또는 성분에 한하여 신청이 가능합니다.\n처리절차\n신청서 작성\nè\n접 수\nè\n검 토\nè\n결 재\nè\n통보\n신청인처리기관: 식품의약품안전처(일반식품 기능성 표시 담당 부서)\n210mm×297mm[백상지(80g/㎡) 또는 중질지(80g/㎡)]\n\n[도안]기능성표시서식도안(제6조제1항관련)\n제 품 명○○○ ○○\n▪(예시) 이 제품은 ○○○를 사용한 \n제품과 같은 시설에서 제조\n▪(타법 의무표시사항 예시) 정당한 소\n비자의 피해에 대해 교환, 환불\n▪(업체 추가표시사항 예시)서늘하고 \n건조한 곳에 보관\n▪부정.불량식품 신고 : 국번없이 1399\n▪(업체 추가표시사항 예시)  고객상담실 : ○○○-○○○-○○○○\n식품유형\n○○○(○○○○○○*)\n*기타표시사항\n영업소(장)의 \n명칭(상호) 및 소재지\n○○식품, ○○시○○구○○로\n○○길○○\n소비기한○○년○○월○○일까지\n내 용 량○○○ g\n원재료명\n○○, ○○○○, ○○○○○○, \n○○○○○, ○○, ○○○○○",
    "metadata": {
      "law": "부당한 표시 또는 광고로 보지 아니하는 식품등의 기능성 표시 또는 광고에 관한 규정",
      "law_number": "2024-62호",
      "category": "admin_rule",
      "chunk_index": 27,
      "total_chunks": 28,
      "effective_date": "2025-01-01",
      "char_count": 600
    }
  },
  {
    "id": "admin_부당한_표시_또는_광고로_보지_아니하_0028",
    "text": "○○○-○○○-○○○○\n식품유형\n○○○(○○○○○○*)\n*기타표시사항\n영업소(장)의 \n명칭(상호) 및 소재지\n○○식품, ○○시○○구○○로\n○○길○○\n소비기한○○년○○월○○일까지\n내 용 량○○○ g\n원재료명\n○○, ○○○○, ○○○○○○, \n○○○○○, ○○, ○○○○○\n○○, ○○○, ○○○○○\n○○*, ○○○*, ○○* 함유\n(*알레르기 유발물질)\n성분명 및 함량○○○(○○mg)\n기능성\n표시\n기능성 성분 함량\n(총 내용량 당)\n○○○으로서 (○○mg)\n1일 섭취기준량\n○○○으로서 (○○mg)\n섭취시 주의사항\n○○○○○○○○○○○○\n균형 잡힌 식생활을 권장합니다. \n이상사례가 있는 경우 섭취를 중단\n하고 전문가와 상담이 필요합니다.\n본 제품은 질병의 예방·치료를 위한 \n제품이 아닙니다.\n영양성분\n(주표시면 표시 가능)\n용기(포장)재질○○○○○\n품목보고번호○○○○○○○○○○○-○○○",
    "metadata": {
      "law": "부당한 표시 또는 광고로 보지 아니하는 식품등의 기능성 표시 또는 광고에 관한 규정",
      "law_number": "2024-62호",
      "category": "admin_rule",
      "chunk_index": 28,
      "total_chunks": 28,
      "effective_date": "2025-01-01",
      "char_count": 442
    }
  }
]